LICENSE
MANIFEST.in
README.rst
requirements.txt
setup.cfg
setup.py
elex/__init__.py
elex/cachecontrol_heuristics.py
elex/exceptions.py
elex.egg-info/PKG-INFO
elex.egg-info/SOURCES.txt
elex.egg-info/dependency_links.txt
elex.egg-info/entry_points.txt
elex.egg-info/requires.txt
elex.egg-info/top_level.txt
elex/api/__init__.py
elex/api/delegates.py
elex/api/maps.py
elex/api/models.py
elex/api/trends.py
elex/api/utils.py
elex/cli/__init__.py
elex/cli/app.py
elex/cli/constants.py
elex/cli/decorators.py
elex/cli/ext_csv.py
elex/cli/ext_json.py
elex/cli/hooks.py
elex/cli/utils.py
tests/__init__.py
tests/test_ap_network.py
tests/test_ap_quota.py
tests/test_ballot_measure.py
tests/test_candidate.py
tests/test_candidate_reporting_unit.py
tests/test_cli.py
tests/test_delegate_reports.py
tests/test_election_district_results.py
tests/test_new_england_reporting_units.py
tests/test_pre_results_candidate.py
tests/test_race.py
tests/test_results.py
tests/test_trend_reports.py