Metadata-Version: 1.1
Name: elex
Version: 2.4.4
Summary: Client for parsing the Associated Press's elections API
Home-page: https://github.com/newsdev/elex
Author: Jeremy Bowers, David Eads
Author-email: jeremy.bowers@nytimes.com, davideads@gmail.com
License: Apache License 2.0
Keywords: election race candidate democracy news associated press
Platform: UNKNOWN
Classifier: Development Status :: 5 - Production/Stable
Classifier: Intended Audience :: Developers
Classifier: Topic :: Software Development :: Libraries :: Python Modules
Classifier: Programming Language :: Python
Classifier: Programming Language :: Python :: 2
Classifier: Programming Language :: Python :: 2.7
Classifier: Programming Language :: Python :: 3
Classifier: Programming Language :: Python :: 3.6
